bay/__init__.py
bay/config.py
bay/constants.py
bay/exceptions.py
bay/version.py
bay/cli/__init__.py
bay/cli/alias_group.py
bay/cli/argument_types.py
bay/cli/colors.py
bay/cli/progress_printer.py
bay/cli/spell.py
bay/cli/table.py
bay/cli/tasks.py
bay/containers/container.py
bay/containers/formation.py
bay/containers/graph.py
bay/containers/profile.py
bay/containers/volumes.py
bay/docker/build.py
bay/docker/hosts.py
bay/docker/images.py
bay/docker/introspect.py
bay/docker/io.py
bay/docker/runner.py
bay/docker/towline.py
bay/plugins/attach.py
bay/plugins/base.py
bay/plugins/boot.py
bay/plugins/build.py
bay/plugins/build_scripts.py
bay/plugins/container.py
bay/plugins/doctor.py
bay/plugins/gc.py
bay/plugins/help.py
bay/plugins/hosts.py
bay/plugins/images.py
bay/plugins/legacy_env.py
bay/plugins/mounts.py
bay/plugins/profile.py
bay/plugins/ps.py
bay/plugins/registry.py
bay/plugins/run.py
bay/plugins/ssh_agent.py
bay/plugins/system.py
bay/plugins/tail.py
bay/plugins/volume.py
bay/plugins/waits.py
bay/utils/functional.py
bay/utils/humanize.py
bay/utils/net.py
bay/utils/sorting.py
bay/utils/threading.py
bay-2.8.1.dist-info/DESCRIPTION.rst
bay-2.8.1.dist-info/METADATA
bay-2.8.1.dist-info/RECORD
bay-2.8.1.dist-info/WHEEL
bay-2.8.1.dist-info/entry_points.txt
bay-2.8.1.dist-info/metadata.json
bay-2.8.1.dist-info/top_level.txt
